PatchTool/__init__.py
PatchTool/acllm.py
PatchTool/func.py
PatchTool/llm.py
PatchTool/sos.py
Patcher_Pro-1.0.0.dist-info/METADATA
Patcher_Pro-1.0.0.dist-info/WHEEL
Patcher_Pro-1.0.0.dist-info/entry_points.txt
Patcher_Pro-1.0.0.dist-info/top_level.txt
Patcher_Pro-1.0.0.dist-info/RECORD
