Metadata-Version: 2.1
Name: Patcher-Pro
Version: 1.0.0
Summary: A tool for various automation and query tasks.
Home-page: https://github.com/aayushmanrepo/patcher
Author: Aayushman Katariya
Author-email: sukrinogreg@gmail.com
License: UNKNOWN
Platform: UNKNOWN
Classifier: Programming Language :: Python :: 3
Classifier: License :: OSI Approved :: MIT License
Requires-Python: >=3.6
Requires-Dist: typer==0.9.0
Requires-Dist: requests>=2.0.0
Requires-Dist: groq
